{
  "city": "chongqing",
  "aircraft": [
    {
      "id": "CHO-01",
      "callsign": "渝配-01",
      "type": "delivery",
      "typeName": "物流配送",
      "color": "#00cc66",
      "speed": 20,
      "route": [
        [
          106.5,
          29.53,
          180
        ],
        [
          106.55,
          29.53,
          180
        ],
        [
          106.6,
          29.53,
          180
        ],
        [
          106.65,
          29.53,
          180
        ],
        [
          106.65,
          29.55,
          190
        ],
        [
          106.6,
          29.55,
          190
        ],
        [
          106.55,
          29.55,
          190
        ],
        [
          106.5,
          29.55,
          190
        ],
        [
          106.5,
          29.57,
          200
        ],
        [
          106.55,
          29.57,
          200
        ],
        [
          106.6,
          29.57,
          200
        ],
        [
          106.65,
          29.57,
          200
        ],
        [
          106.65,
          29.59,
          190
        ],
        [
          106.6,
          29.59,
          190
        ],
        [
          106.55,
          29.59,
          190
        ],
        [
          106.5,
          29.59,
          190
        ],
        [
          106.5,
          29.61,
          200
        ],
        [
          106.55,
          29.61,
          200
        ],
        [
          106.6,
          29.61,
          200
        ],
        [
          106.65,
          29.61,
          200
        ]
      ],
      "battery": 95,
      "status": "cruising"
    },
    {
      "id": "CHO-02",
      "callsign": "渝巡-02",
      "type": "patrol",
      "typeName": "山城巡检",
      "color": "#ff8800",
      "speed": 15,
      "route": [
        [
          106.52,
          29.52,
          200
        ],
        [
          106.57,
          29.52,
          220
        ],
        [
          106.62,
          29.54,
          240
        ],
        [
          106.65,
          29.56,
          260
        ],
        [
          106.63,
          29.58,
          280
        ],
        [
          106.58,
          29.6,
          300
        ],
        [
          106.53,
          29.59,
          320
        ],
        [
          106.5,
          29.57,
          340
        ],
        [
          106.52,
          29.55,
          320
        ],
        [
          106.55,
          29.53,
          280
        ],
        [
          106.52,
          29.52,
          200
        ]
      ],
      "battery": 92,
      "status": "cruising"
    },
    {
      "id": "CHO-03",
      "callsign": "渝渡-03",
      "type": "ferry",
      "typeName": "两江摆渡",
      "color": "#ffaa00",
      "speed": 35,
      "route": [
        [
          106.55,
          29.55,
          260
        ],
        [
          106.62,
          29.57,
          260
        ],
        [
          106.62,
          29.6,
          260
        ],
        [
          106.55,
          29.62,
          260
        ],
        [
          106.55,
          29.58,
          260
        ],
        [
          106.5,
          29.56,
          260
        ],
        [
          106.55,
          29.55,
          260
        ]
      ],
      "battery": 89,
      "status": "cruising"
    },
    {
      "id": "CHO-04",
      "callsign": "渝通-04",
      "type": "evtol",
      "typeName": "载人通勤",
      "color": "#ff4444",
      "speed": 50,
      "route": [
        [
          106.55,
          29.6,
          850
        ],
        [
          106.57,
          29.58,
          850
        ],
        [
          106.58,
          29.56,
          850
        ],
        [
          106.57,
          29.54,
          850
        ],
        [
          106.55,
          29.52,
          850
        ],
        [
          106.57,
          29.54,
          850
        ],
        [
          106.58,
          29.56,
          850
        ],
        [
          106.57,
          29.58,
          850
        ],
        [
          106.55,
          29.6,
          850
        ]
      ],
      "battery": 86,
      "status": "cruising"
    },
    {
      "id": "CHO-05",
      "callsign": "渝急-05",
      "type": "emergency",
      "typeName": "应急救援",
      "color": "#ff0000",
      "speed": 40,
      "route": [
        [
          106.48,
          29.52,
          300
        ],
        [
          106.55,
          29.5,
          300
        ],
        [
          106.62,
          29.53,
          300
        ],
        [
          106.67,
          29.56,
          300
        ],
        [
          106.65,
          29.6,
          300
        ],
        [
          106.58,
          29.64,
          300
        ],
        [
          106.5,
          29.62,
          300
        ],
        [
          106.47,
          29.56,
          300
        ],
        [
          106.48,
          29.52,
          300
        ]
      ],
      "battery": 83,
      "status": "cruising"
    }
  ]
}